{"flags":{"chest":"[1, 1, 1, 1]"},"items":{"inventory":"{\nResource(\"res://data/items/items/Apple.tres\"): 2,\nResource(\"res://data/items/items/Banana.tres\"): 1,\nResource(\"res://data/items/items/Hammer.tres\"): 2,\nResource(\"res://data/items/items/Red_Orb.tres\"): 1,\nResource(\"res://data/items/items/Sword.tres\"): 1,\nResource(\"res://data/items/items/Wooden_Shield.tres\"): 1\n}"},"player":{"activemap":"\"test_area\"","gold":"1000","party":"[\"Lucia\", \"Renzo\"]","spawnx":"592.0","spawny":"260.0"}}
